zodipy/__init__.py
zodipy/blackbody.py
zodipy/bodies.py
zodipy/brightness.py
zodipy/component.py
zodipy/component_params.py
zodipy/line_of_sight.py
zodipy/model.py
zodipy/model_registry.py
zodipy/number_density.py
zodipy/py.typed
zodipy/scattering.py
zodipy/source_params.py
zodipy/unpack_model.py
zodipy/zodiacal_light_model.py
zodipy-1.1.2.dist-info/LICENSE
zodipy-1.1.2.dist-info/METADATA
zodipy-1.1.2.dist-info/WHEEL
zodipy-1.1.2.dist-info/RECORD
