Metadata-Version: 2.3
Name: zodipy
Version: 1.1.2
Summary: A Python package for zodiacal light simulations
License: GPL-3.0-or-later
Keywords: astronomy,astrophysics,cosmology,space,science
Author: Metin San
Author-email: metinisan@gmail.com
Requires-Python: >=3.9
Classifier: Intended Audience :: Science/Research
Classifier: License :: OSI Approved :: GNU General Public License v3 or later (GPLv3+)
Classifier: Operating System :: OS Independent
Classifier: Programming Language :: Python :: 3
Classifier: Programming Language :: Python :: 3.9
Classifier: Programming Language :: Python :: 3.10
Classifier: Programming Language :: Python :: 3.11
Classifier: Programming Language :: Python :: 3.12
Classifier: Programming Language :: Python :: 3.13
Classifier: Topic :: Scientific/Engineering :: Astronomy
Classifier: Topic :: Scientific/Engineering :: Physics
Requires-Dist: astropy (>=5.0.1)
Requires-Dist: jplephem (>=2.17,<3.0)
Requires-Dist: numpy (>=1.26.4,<2.0.0)
Requires-Dist: scipy (>=1.13.0,<2.0.0)
Project-URL: documentation, https://cosmoglobe.github.io/zodipy/
Project-URL: repository, https://github.com/cosmoglobe/zodipy
